{
    "name": "in_trees_64",
    "task_graph": {
        "tasks": [
            {
                "name": "T0",
                "cost": 2.0
            },
            {
                "name": "T4",
                "cost": 2.0
            },
            {
                "name": "T3",
                "cost": 2.0
            },
            {
                "name": "T2",
                "cost": 2.0
            },
            {
                "name": "T5",
                "cost": 2.0
            },
            {
                "name": "T7",
                "cost": 1e-9
            },
            {
                "name": "T1",
                "cost": 2.0
            },
            {
                "name": "T6",
                "cost": 2.0
            }
        ],
        "dependencies": [
            {
                "source": "T6",
                "target": "T2",
                "size": 2.0
            },
            {
                "source": "T7",
                "target": "T3",
                "size": 1e-9
            },
            {
                "source": "T4",
                "target": "T1",
                "size": 2.0
            },
            {
                "source": "T3",
                "target": "T1",
                "size": 2.0
            },
            {
                "source": "T7",
                "target": "T4",
                "size": 1e-9
            },
            {
                "source": "T2",
                "target": "T0",
                "size": 2.0
            },
            {
                "source": "T5",
                "target": "T2",
                "size": 2.0
            },
            {
                "source": "T7",
                "target": "T5",
                "size": 1e-9
            },
            {
                "source": "T7",
                "target": "T6",
                "size": 1e-9
            },
            {
                "source": "T1",
                "target": "T0",
                "size": 2.0
            }
        ]
    },
    "network": {
        "nodes": [
            {
                "name": "N2",
                "speed": 2.0
            },
            {
                "name": "N0",
                "speed": 2.0
            },
            {
                "name": "N3",
                "speed": 2.0
            },
            {
                "name": "N1",
                "speed": 2.0
            }
        ],
        "edges": [
            {
                "source": "N1",
                "target": "N2",
                "speed": 2.0
            },
            {
                "source": "N0",
                "target": "N3",
                "speed": 2.0
            },
            {
                "source": "N2",
                "target": "N2",
                "speed": 1000000000.0
            },
            {
                "source": "N1",
                "target": "N3",
                "speed": 2.0
            },
            {
                "source": "N0",
                "target": "N1",
                "speed": 2.0
            },
            {
                "source": "N2",
                "target": "N3",
                "speed": 2.0
            },
            {
                "source": "N1",
                "target": "N1",
                "speed": 1000000000.0
            },
            {
                "source": "N3",
                "target": "N3",
                "speed": 1000000000.0
            },
            {
                "source": "N0",
                "target": "N0",
                "speed": 1000000000.0
            },
            {
                "source": "N0",
                "target": "N2",
                "speed": 2.0
            }
        ]
    }
}